{"moderation":[["ban","Bans the specified user.","yes ban [user]","","3 seconds"],["kick","Kicks the specified user.","yes kick [user]","","3 seconds"],["purge","Allows you to mass delete messages in your server.","yes purge [#msgs]","prune\nclear\nwipe","10 seconds"]],"game":[["battle","Start a battle.","yes battle","","5 seconds"],["daily","Claim your daily reward.","yes daily","","23 hours"],["fish","Do your fishing.","yes fish\nyes fish stats","","3 seconds"],["gamble","Gamble your points away.","yes gamble [points]\nyes gamble all","","5 seconds"],["pet","Displays your pet.","yes pet\nyes pet feed\nyes pet wash\nyes pet play\nyes pet pat\nyes pet name\nyes pet disown\nyes pet list\nyes pet buy","","4 seconds"],["profile","Displays your profile.","yes profile [@user/id]","","5 seconds"],["start","Begin your adventure up the Tower.","yes start","","1 minute"],["stats","Display your stats and stat points.","yes stats","","5 seconds"],["top","Displays the top players.","yes top\nyes top points\nyes top dallars\nyes top reputation\nyes top fish","leaderboard","4 seconds"]],"info":[["avatar","Links a URL to the avatar of the mentioned user.","yes avatar [@user/id]","icon\npfp","5 seconds"],["channelinfo","Displays info about the mentioned channel.","yes channelinfo","","5 seconds"],["help","Shows the command list.","yes help","commands","5 seconds"],["owner","Shows the owner of this bot.","yes owner","","3 seconds"],["serverinfo","Displays info about the server.","yes serverinfo","","5 seconds"],["userinfo","Display the user mentioned's info.","yes userinfo [@user/id]","whois","5 seconds"]],"social":[["gif","Displays a random gif based on the provided tag or category.","yes gif [keyword]","","2 seconds"]],"utility":[["anime","Displays info of the requested anime.","yes anime [anime]","","10 seconds"],["lyrics","Display the lyrics of the requested song.","yes lyrics [song]","","10 seconds"],["manga","Displays info of the requested manga.","yes manga [manga]","","10 seconds"],["math","Calculates the provided equation.","yes math [equation]","math\ncalculate\nevaluate","2 seconds"],["translate","Translates the text into the specified language.","yes translate [language/ISO 639-1] [text]","ts","5 seconds"],["urban","Look up a term on Urban Dictionary. (NSFW)","yes urban [term]","","10 seconds"],["weather","Displays weather info on the provided city.","yes weather [place/postal code]","","10 seconds"]]}